metaapi_cloud_copyfactory_sdk/__init__.py
metaapi_cloud_copyfactory_sdk/copyfactory.py
metaapi_cloud_copyfactory_sdk/logger.py
metaapi_cloud_copyfactory_sdk/models.py
metaapi_cloud_copyfactory_sdk/clients/__init__.py
metaapi_cloud_copyfactory_sdk/clients/domain_client.py
metaapi_cloud_copyfactory_sdk/clients/domain_client_test.py
metaapi_cloud_copyfactory_sdk/clients/error_handler.py
metaapi_cloud_copyfactory_sdk/clients/http_client.py
metaapi_cloud_copyfactory_sdk/clients/http_client_test.py
metaapi_cloud_copyfactory_sdk/clients/metaapi_client.py
metaapi_cloud_copyfactory_sdk/clients/metaapi_client_test.py
metaapi_cloud_copyfactory_sdk/clients/method_access_exception.py
metaapi_cloud_copyfactory_sdk/clients/timeout_exception.py
metaapi_cloud_copyfactory_sdk/clients/copyfactory/__init__.py
metaapi_cloud_copyfactory_sdk/clients/copyfactory/configuration_client.py
metaapi_cloud_copyfactory_sdk/clients/copyfactory/configuration_client_test.py
metaapi_cloud_copyfactory_sdk/clients/copyfactory/copyfactory_models.py
metaapi_cloud_copyfactory_sdk/clients/copyfactory/history_client.py
metaapi_cloud_copyfactory_sdk/clients/copyfactory/history_client_test.py
metaapi_cloud_copyfactory_sdk/clients/copyfactory/strategy_signal_client.py
metaapi_cloud_copyfactory_sdk/clients/copyfactory/strategy_signal_client_test.py
metaapi_cloud_copyfactory_sdk/clients/copyfactory/subscriber_signal_client.py
metaapi_cloud_copyfactory_sdk/clients/copyfactory/subscriber_signal_client_test.py
metaapi_cloud_copyfactory_sdk/clients/copyfactory/trading_client.py
metaapi_cloud_copyfactory_sdk/clients/copyfactory/trading_client_test.py
metaapi_cloud_copyfactory_sdk/clients/copyfactory/streaming/__init__.py
metaapi_cloud_copyfactory_sdk/clients/copyfactory/streaming/stopout_listener.py
metaapi_cloud_copyfactory_sdk/clients/copyfactory/streaming/stopout_listener_manager.py
metaapi_cloud_copyfactory_sdk/clients/copyfactory/streaming/stopout_listener_manager_test.py
metaapi_cloud_copyfactory_sdk-11.1.1.dist-info/LICENSE
metaapi_cloud_copyfactory_sdk-11.1.1.dist-info/METADATA
metaapi_cloud_copyfactory_sdk-11.1.1.dist-info/WHEEL
metaapi_cloud_copyfactory_sdk-11.1.1.dist-info/top_level.txt
metaapi_cloud_copyfactory_sdk-11.1.1.dist-info/RECORD
