Metadata-Version: 2.2
Name: metaapi_cloud_copyfactory_sdk
Version: 11.1.1
Summary: Python SDK for SDK for CopyFactory trade copying API. Can copy trades both between MetaTrader 5 (MT5) and MetaTrader 4 (MT4). (https://metaapi.cloud)
Author-email: MetaApi <support@metaapi.cloud>
License: (c) Copyright 2020-2023 MetaApi DMCC. All rights reserved
Project-URL: Homepage, https://github.com/metaapi/metaapi-copyfactory-python-sdk
Keywords: metaapi.cloud,MetaTrader,MetaTrader 5,MetaTrader 4,MetaTrader5,MetaTrader4,MT,MT4,MT5,forex,copy trading,API,REST,client,sdk,cloud
Classifier: Programming Language :: Python :: 3
Classifier: License :: Other/Proprietary License
Classifier: Operating System :: OS Independent
Requires-Python: >=3.8
License-File: LICENSE
Requires-Dist: typing-extensions>=4.0.0
Requires-Dist: iso8601
Requires-Dist: pytz
Requires-Dist: httpx<0.28.0,>=0.27.0
Provides-Extra: test
Requires-Dist: pytest==6.2.5; extra == "test"
Requires-Dist: pytest-mock; extra == "test"
Requires-Dist: pytest-asyncio==0.16.0; extra == "test"
Requires-Dist: asynctest; extra == "test"
Requires-Dist: mock; extra == "test"
Requires-Dist: freezegun==1.0.0; extra == "test"
Requires-Dist: respx==0.21.1; extra == "test"
